{
  "name": "@interface/sdk_cangjie",
  "description": "openharmony cangjie sdk",
  "version": "6.0",
  "license": "Apache License 2.0",
  "supplier": "Organization: OpenHarmony",
  "publishAs": "code-segment",
  "segment": {
    "destPath": "interface/sdk_cangjie"
  },
  "readmePath": {
    "zh": "README_zh.md"
  },
  "dirs": {},
  "scripts": {},
  "component": {
    "name": "interface_sdk_cangjie",
    "description": "openharmony cangjie sdk",
    "subsystem": "sdk",
    "features": [],
    "adapted_system_type": [
      "standard"
    ],
    "rom": "",
    "ram": "",
    "deps": {
      "components": [
        "cangjie_ark_interop",
        "arkui_cangjie_wrapper"
      ]
    },
    "build": {
      "sub_component": [],
      "inner_api": [],
      "test": []
    }
  }
}