{
  version: "1.0.0",
  cjoVersion: {
    major_num: 0,
    minor_num: 1,
    patch_num: 0
  },
  fullPkgName: "ohos.arkui.component.grid_item",
  pkgDepInfo: "{\"package\":\"ohos.arkui.component.grid_item\",\"isMacro\":false,\"accessLevel\":\"public\",\"dependencies\":[{\"package\":\"ohos.arkui.component.common\",\"isStd\":false,\"imports\":[{\"file\":\"cj_grid_item.cj\",\"begin\":{\"line\":18,\"column\":1},\"end\":{\"line\":18,\"column\":37}}]},{\"package\":\"ohos.labels\",\"isStd\":false,\"imports\":[{\"file\":\"cj_grid_item.cj\",\"begin\":{\"line\":19,\"column\":1},\"end\":{\"line\":19,\"column\":28}}]}]}",
  imports: [
    "ohos.arkui.component.common"
  ],
  allFiles: [
    "ohos.arkui.component.grid_item/cj_grid_item.cj"
  ],
  allFileImports: [
    {
      importSpecs: [
        {
          begin: {
            file: 1,
            pkgId: 0,
            line: 18,
            column: 1,
            ignore: false
          },
          end: {
            file: 1,
            pkgId: 0,
            line: 18,
            column: 37,
            ignore: false
          },
          prefixPaths: [
            "ohos",
            "arkui",
            "component",
            "common"
          ],
          identifier: "*",
          asIdentifier: ""
        },
        {
          begin: {
            file: 1,
            pkgId: 0,
            line: 19,
            column: 1,
            ignore: false
          },
          end: {
            file: 1,
            pkgId: 0,
            line: 19,
            column: 28,
            ignore: false
          },
          prefixPaths: [
            "ohos",
            "labels"
          ],
          identifier: "APILevel",
          asIdentifier: ""
        },
        {
          begin: {
            file: 1,
            pkgId: 0,
            line: 0,
            column: 0,
            ignore: false
          },
          end: {
            file: 1,
            pkgId: 0,
            line: 0,
            column: 0,
            ignore: false
          },
          prefixPaths: [
            "std",
            "core"
          ],
          identifier: "*",
          asIdentifier: ""
        }
      ]
    }
  ],
  allTypes: [
    {
      kind: "Func",
      typeArgs: [

      ],
      info_type: "FuncTyInfo",
      info: {
        retType: 2,
        isC: true
      }
    },
    {
    },
    {
      kind: "Func",
      typeArgs: [
        4
      ],
      info_type: "FuncTyInfo",
      info: {
        retType: 2,
        isC: true
      }
    },
    {
      kind: "Int32"
    },
    {
      kind: "Func",
      typeArgs: [
        6
      ],
      info_type: "FuncTyInfo",
      info: {
        retType: 2,
        isC: true
      }
    },
    {
      kind: "Bool"
    },
    {
      kind: "Func",
      typeArgs: [
        8
      ],
      info_type: "FuncTyInfo",
      info: {
        retType: 2,
        isC: true
      }
    },
    {
      kind: "Int64"
    },
    {
      kind: "Class",
      typeArgs: [

      ],
      info_type: "CompositeTyInfo",
      info: {
        declPtr: {
          pkgId: -2,
          index: 20
        }
      }
    },
    {
      kind: "Func",
      typeArgs: [

      ],
      info_type: "FuncTyInfo",
      info: {
        retType: 9
      }
    },
    {
      kind: "Func",
      typeArgs: [
        12
      ],
      info_type: "FuncTyInfo",
      info: {
        retType: 9
      }
    },
    {
      kind: "Func",
      typeArgs: [

      ],
      info_type: "FuncTyInfo",
      info: {
        retType: 2
      }
    },
    {
      kind: "Func",
      typeArgs: [
        4
      ],
      info_type: "FuncTyInfo",
      info: {
        retType: 14
      }
    },
    {
      kind: "Class",
      typeArgs: [

      ],
      info_type: "CompositeTyInfo",
      info: {
        declPtr: {
          pkgId: -2,
          index: 20
        },
        isThisTy: true
      }
    },
    {
      kind: "Class",
      typeArgs: [

      ],
      info_type: "CompositeTyInfo",
      info: {
        declPtr: {
          decl: "_CN27ohos.arkui.component.common13ContainerBaseE"
        }
      }
    }
  ],
  allDecls: [
    {
      kind: "FuncDecl",
      isTopLevel: true,
      fullPkgName: "ohos.arkui.component.grid_item",
      genericDecl: {
        pkgId: -1,
        decl: ""
      },
      begin: {
        file: 1,
        pkgId: 0,
        line: 22,
        column: 5,
        ignore: false
      },
      end: {
        file: 1,
        pkgId: 0,
        line: 22,
        column: 51,
        ignore: false
      },
      identifier: "FfiOHOSAceFrameworkGridItemCreate",
      identifierPos: {
        file: 1,
        pkgId: 0,
        line: 22,
        column: 10,
        ignore: false
      },
      attributes: [
        144968409101123632,
        0
      ],
      annotations: [

      ],
      type: 1,
      mangledName: "FfiOHOSAceFrameworkGridItemCreate",
      exportId: "FfiOHOSAceFrameworkGridItemCreate",
      mangledBeforeSema: "30ohos.arkui.component.grid_item33FfiOHOSAceFrameworkGridItemCreateF$$u",
      hash: {
        instVar: 0,
        virt: 0,
        sig: 520285295869893810,
        srcUse: 7222278799635774413,
        bodyHash: 0
      },
      info_type: "FuncInfo",
      info: {
        funcBody: {
          paramLists: [
            {
              params: [

              ],
              desugars: [

              ]
            }
          ],
          retType: 2
        }
      }
    },
    {
      kind: "FuncDecl",
      isTopLevel: true,
      fullPkgName: "ohos.arkui.component.grid_item",
      genericDecl: {
        pkgId: -1,
        decl: ""
      },
      begin: {
        file: 1,
        pkgId: 0,
        line: 24,
        column: 5,
        ignore: false
      },
      end: {
        file: 1,
        pkgId: 0,
        line: 24,
        column: 74,
        ignore: false
      },
      identifier: "FfiOHOSAceFrameworkGridItemCreateWithOptions",
      identifierPos: {
        file: 1,
        pkgId: 0,
        line: 24,
        column: 10,
        ignore: false
      },
      attributes: [
        144968409101123632,
        0
      ],
      annotations: [

      ],
      type: 3,
      mangledName: "FfiOHOSAceFrameworkGridItemCreateWithOptions",
      exportId: "FfiOHOSAceFrameworkGridItemCreateWithOptions",
      mangledBeforeSema: "30ohos.arkui.component.grid_item44FfiOHOSAceFrameworkGridItemCreateWithOptionsFi$$u",
      hash: {
        instVar: 0,
        virt: 0,
        sig: 520285295869893810,
        srcUse: 7222278799635774413,
        bodyHash: 8408041226178326877
      },
      info_type: "FuncInfo",
      info: {
        funcBody: {
          paramLists: [
            {
              params: [
                3
              ],
              desugars: [
                0
              ]
            }
          ],
          retType: 2
        }
      }
    },
    {
      kind: "FuncParam",
      fullPkgName: "ohos.arkui.component.grid_item",
      begin: {
        file: 1,
        pkgId: 0,
        line: 24,
        column: 55,
        ignore: false
      },
      end: {
        file: 1,
        pkgId: 0,
        line: 24,
        column: 67,
        ignore: false
      },
      identifier: "value",
      identifierPos: {
        file: 1,
        pkgId: 0,
        line: 24,
        column: 55,
        ignore: false
      },
      attributes: [
        562949953421344,
        0
      ],
      annotations: [

      ],
      type: 4,
      mangledName: "_CN30ohos.arkui.component.grid_item44FfiOHOSAceFrameworkGridItemCreateWithOptionsHiE5valueE",
      exportId: "",
      mangledBeforeSema: "",
      hash: {
        instVar: 0,
        virt: 0,
        sig: 0,
        srcUse: 0,
        bodyHash: 0
      },
      info_type: "ParamInfo",
      info: {
      }
    },
    {
      kind: "FuncDecl",
      isTopLevel: true,
      fullPkgName: "ohos.arkui.component.grid_item",
      genericDecl: {
        pkgId: -1,
        decl: ""
      },
      begin: {
        file: 1,
        pkgId: 0,
        line: 26,
        column: 5,
        ignore: false
      },
      end: {
        file: 1,
        pkgId: 0,
        line: 26,
        column: 77,
        ignore: false
      },
      identifier: "FfiOHOSAceFrameworkGridItemSetColumnStart",
      identifierPos: {
        file: 1,
        pkgId: 0,
        line: 26,
        column: 10,
        ignore: false
      },
      attributes: [
        144968409101123632,
        0
      ],
      annotations: [

      ],
      type: 3,
      mangledName: "FfiOHOSAceFrameworkGridItemSetColumnStart",
      exportId: "FfiOHOSAceFrameworkGridItemSetColumnStart",
      mangledBeforeSema: "30ohos.arkui.component.grid_item41FfiOHOSAceFrameworkGridItemSetColumnStartFi$$u",
      hash: {
        instVar: 0,
        virt: 0,
        sig: 520285295869893810,
        srcUse: 7222278799635774413,
        bodyHash: 7022800694274263824
      },
      info_type: "FuncInfo",
      info: {
        funcBody: {
          paramLists: [
            {
              params: [
                5
              ],
              desugars: [
                0
              ]
            }
          ],
          retType: 2
        }
      }
    },
    {
      kind: "FuncParam",
      fullPkgName: "ohos.arkui.component.grid_item",
      begin: {
        file: 1,
        pkgId: 0,
        line: 26,
        column: 52,
        ignore: false
      },
      end: {
        file: 1,
        pkgId: 0,
        line: 26,
        column: 70,
        ignore: false
      },
      identifier: "columnStart",
      identifierPos: {
        file: 1,
        pkgId: 0,
        line: 26,
        column: 52,
        ignore: false
      },
      attributes: [
        562949953421344,
        0
      ],
      annotations: [

      ],
      type: 4,
      mangledName: "_CN30ohos.arkui.component.grid_item41FfiOHOSAceFrameworkGridItemSetColumnStartHiE11columnStartE",
      exportId: "",
      mangledBeforeSema: "",
      hash: {
        instVar: 0,
        virt: 0,
        sig: 0,
        srcUse: 0,
        bodyHash: 0
      },
      info_type: "ParamInfo",
      info: {
      }
    },
    {
      kind: "FuncDecl",
      isTopLevel: true,
      fullPkgName: "ohos.arkui.component.grid_item",
      genericDecl: {
        pkgId: -1,
        decl: ""
      },
      begin: {
        file: 1,
        pkgId: 0,
        line: 28,
        column: 5,
        ignore: false
      },
      end: {
        file: 1,
        pkgId: 0,
        line: 28,
        column: 73,
        ignore: false
      },
      identifier: "FfiOHOSAceFrameworkGridItemSetColumnEnd",
      identifierPos: {
        file: 1,
        pkgId: 0,
        line: 28,
        column: 10,
        ignore: false
      },
      attributes: [
        144968409101123632,
        0
      ],
      annotations: [

      ],
      type: 3,
      mangledName: "FfiOHOSAceFrameworkGridItemSetColumnEnd",
      exportId: "FfiOHOSAceFrameworkGridItemSetColumnEnd",
      mangledBeforeSema: "30ohos.arkui.component.grid_item39FfiOHOSAceFrameworkGridItemSetColumnEndFi$$u",
      hash: {
        instVar: 0,
        virt: 0,
        sig: 520285295869893810,
        srcUse: 7222278799635774413,
        bodyHash: 8017669586100189881
      },
      info_type: "FuncInfo",
      info: {
        funcBody: {
          paramLists: [
            {
              params: [
                7
              ],
              desugars: [
                0
              ]
            }
          ],
          retType: 2
        }
      }
    },
    {
      kind: "FuncParam",
      fullPkgName: "ohos.arkui.component.grid_item",
      begin: {
        file: 1,
        pkgId: 0,
        line: 28,
        column: 50,
        ignore: false
      },
      end: {
        file: 1,
        pkgId: 0,
        line: 28,
        column: 66,
        ignore: false
      },
      identifier: "columnEnd",
      identifierPos: {
        file: 1,
        pkgId: 0,
        line: 28,
        column: 50,
        ignore: false
      },
      attributes: [
        562949953421344,
        0
      ],
      annotations: [

      ],
      type: 4,
      mangledName: "_CN30ohos.arkui.component.grid_item39FfiOHOSAceFrameworkGridItemSetColumnEndHiE9columnEndE",
      exportId: "",
      mangledBeforeSema: "",
      hash: {
        instVar: 0,
        virt: 0,
        sig: 0,
        srcUse: 0,
        bodyHash: 0
      },
      info_type: "ParamInfo",
      info: {
      }
    },
    {
      kind: "FuncDecl",
      isTopLevel: true,
      fullPkgName: "ohos.arkui.component.grid_item",
      genericDecl: {
        pkgId: -1,
        decl: ""
      },
      begin: {
        file: 1,
        pkgId: 0,
        line: 30,
        column: 5,
        ignore: false
      },
      end: {
        file: 1,
        pkgId: 0,
        line: 30,
        column: 71,
        ignore: false
      },
      identifier: "FfiOHOSAceFrameworkGridItemSetRowStart",
      identifierPos: {
        file: 1,
        pkgId: 0,
        line: 30,
        column: 10,
        ignore: false
      },
      attributes: [
        144968409101123632,
        0
      ],
      annotations: [

      ],
      type: 3,
      mangledName: "FfiOHOSAceFrameworkGridItemSetRowStart",
      exportId: "FfiOHOSAceFrameworkGridItemSetRowStart",
      mangledBeforeSema: "30ohos.arkui.component.grid_item38FfiOHOSAceFrameworkGridItemSetRowStartFi$$u",
      hash: {
        instVar: 0,
        virt: 0,
        sig: 520285295869893810,
        srcUse: 7222278799635774413,
        bodyHash: 7899648630570217775
      },
      info_type: "FuncInfo",
      info: {
        funcBody: {
          paramLists: [
            {
              params: [
                9
              ],
              desugars: [
                0
              ]
            }
          ],
          retType: 2
        }
      }
    },
    {
      kind: "FuncParam",
      fullPkgName: "ohos.arkui.component.grid_item",
      begin: {
        file: 1,
        pkgId: 0,
        line: 30,
        column: 49,
        ignore: false
      },
      end: {
        file: 1,
        pkgId: 0,
        line: 30,
        column: 64,
        ignore: false
      },
      identifier: "rowStart",
      identifierPos: {
        file: 1,
        pkgId: 0,
        line: 30,
        column: 49,
        ignore: false
      },
      attributes: [
        562949953421344,
        0
      ],
      annotations: [

      ],
      type: 4,
      mangledName: "_CN30ohos.arkui.component.grid_item38FfiOHOSAceFrameworkGridItemSetRowStartHiE8rowStartE",
      exportId: "",
      mangledBeforeSema: "",
      hash: {
        instVar: 0,
        virt: 0,
        sig: 0,
        srcUse: 0,
        bodyHash: 0
      },
      info_type: "ParamInfo",
      info: {
      }
    },
    {
      kind: "FuncDecl",
      isTopLevel: true,
      fullPkgName: "ohos.arkui.component.grid_item",
      genericDecl: {
        pkgId: -1,
        decl: ""
      },
      begin: {
        file: 1,
        pkgId: 0,
        line: 32,
        column: 5,
        ignore: false
      },
      end: {
        file: 1,
        pkgId: 0,
        line: 32,
        column: 67,
        ignore: false
      },
      identifier: "FfiOHOSAceFrameworkGridItemSetRowEnd",
      identifierPos: {
        file: 1,
        pkgId: 0,
        line: 32,
        column: 10,
        ignore: false
      },
      attributes: [
        144968409101123632,
        0
      ],
      annotations: [

      ],
      type: 3,
      mangledName: "FfiOHOSAceFrameworkGridItemSetRowEnd",
      exportId: "FfiOHOSAceFrameworkGridItemSetRowEnd",
      mangledBeforeSema: "30ohos.arkui.component.grid_item36FfiOHOSAceFrameworkGridItemSetRowEndFi$$u",
      hash: {
        instVar: 0,
        virt: 0,
        sig: 520285295869893810,
        srcUse: 7222278799635774413,
        bodyHash: 11030169405404925055
      },
      info_type: "FuncInfo",
      info: {
        funcBody: {
          paramLists: [
            {
              params: [
                11
              ],
              desugars: [
                0
              ]
            }
          ],
          retType: 2
        }
      }
    },
    {
      kind: "FuncParam",
      fullPkgName: "ohos.arkui.component.grid_item",
      begin: {
        file: 1,
        pkgId: 0,
        line: 32,
        column: 47,
        ignore: false
      },
      end: {
        file: 1,
        pkgId: 0,
        line: 32,
        column: 60,
        ignore: false
      },
      identifier: "rowEnd",
      identifierPos: {
        file: 1,
        pkgId: 0,
        line: 32,
        column: 47,
        ignore: false
      },
      attributes: [
        562949953421344,
        0
      ],
      annotations: [

      ],
      type: 4,
      mangledName: "_CN30ohos.arkui.component.grid_item36FfiOHOSAceFrameworkGridItemSetRowEndHiE6rowEndE",
      exportId: "",
      mangledBeforeSema: "",
      hash: {
        instVar: 0,
        virt: 0,
        sig: 0,
        srcUse: 0,
        bodyHash: 0
      },
      info_type: "ParamInfo",
      info: {
      }
    },
    {
      kind: "FuncDecl",
      isTopLevel: true,
      fullPkgName: "ohos.arkui.component.grid_item",
      genericDecl: {
        pkgId: -1,
        decl: ""
      },
      begin: {
        file: 1,
        pkgId: 0,
        line: 34,
        column: 5,
        ignore: false
      },
      end: {
        file: 1,
        pkgId: 0,
        line: 34,
        column: 75,
        ignore: false
      },
      identifier: "FfiOHOSAceFrameworkGridItemForceRebuild",
      identifierPos: {
        file: 1,
        pkgId: 0,
        line: 34,
        column: 10,
        ignore: false
      },
      attributes: [
        144968409101123632,
        0
      ],
      annotations: [

      ],
      type: 5,
      mangledName: "FfiOHOSAceFrameworkGridItemForceRebuild",
      exportId: "FfiOHOSAceFrameworkGridItemForceRebuild",
      mangledBeforeSema: "30ohos.arkui.component.grid_item39FfiOHOSAceFrameworkGridItemForceRebuildFb$$u",
      hash: {
        instVar: 0,
        virt: 0,
        sig: 520285295869893810,
        srcUse: 7222278799635774413,
        bodyHash: 18056154716902993008
      },
      info_type: "FuncInfo",
      info: {
        funcBody: {
          paramLists: [
            {
              params: [
                13
              ],
              desugars: [
                0
              ]
            }
          ],
          retType: 2
        }
      }
    },
    {
      kind: "FuncParam",
      fullPkgName: "ohos.arkui.component.grid_item",
      begin: {
        file: 1,
        pkgId: 0,
        line: 34,
        column: 50,
        ignore: false
      },
      end: {
        file: 1,
        pkgId: 0,
        line: 34,
        column: 68,
        ignore: false
      },
      identifier: "forceRebuild",
      identifierPos: {
        file: 1,
        pkgId: 0,
        line: 34,
        column: 50,
        ignore: false
      },
      attributes: [
        562949953421344,
        0
      ],
      annotations: [

      ],
      type: 6,
      mangledName: "_CN30ohos.arkui.component.grid_item39FfiOHOSAceFrameworkGridItemForceRebuildHbE12forceRebuildE",
      exportId: "",
      mangledBeforeSema: "",
      hash: {
        instVar: 0,
        virt: 0,
        sig: 0,
        srcUse: 0,
        bodyHash: 0
      },
      info_type: "ParamInfo",
      info: {
      }
    },
    {
      kind: "FuncDecl",
      isTopLevel: true,
      fullPkgName: "ohos.arkui.component.grid_item",
      genericDecl: {
        pkgId: -1,
        decl: ""
      },
      begin: {
        file: 1,
        pkgId: 0,
        line: 36,
        column: 5,
        ignore: false
      },
      end: {
        file: 1,
        pkgId: 0,
        line: 36,
        column: 66,
        ignore: false
      },
      identifier: "FfiOHOSAceFrameworkGridItemSelectable",
      identifierPos: {
        file: 1,
        pkgId: 0,
        line: 36,
        column: 10,
        ignore: false
      },
      attributes: [
        144968409101123632,
        0
      ],
      annotations: [

      ],
      type: 5,
      mangledName: "FfiOHOSAceFrameworkGridItemSelectable",
      exportId: "FfiOHOSAceFrameworkGridItemSelectable",
      mangledBeforeSema: "30ohos.arkui.component.grid_item37FfiOHOSAceFrameworkGridItemSelectableFb$$u",
      hash: {
        instVar: 0,
        virt: 0,
        sig: 520285295869893810,
        srcUse: 7222278799635774413,
        bodyHash: 8408041226178326877
      },
      info_type: "FuncInfo",
      info: {
        funcBody: {
          paramLists: [
            {
              params: [
                15
              ],
              desugars: [
                0
              ]
            }
          ],
          retType: 2
        }
      }
    },
    {
      kind: "FuncParam",
      fullPkgName: "ohos.arkui.component.grid_item",
      begin: {
        file: 1,
        pkgId: 0,
        line: 36,
        column: 48,
        ignore: false
      },
      end: {
        file: 1,
        pkgId: 0,
        line: 36,
        column: 59,
        ignore: false
      },
      identifier: "value",
      identifierPos: {
        file: 1,
        pkgId: 0,
        line: 36,
        column: 48,
        ignore: false
      },
      attributes: [
        562949953421344,
        0
      ],
      annotations: [

      ],
      type: 6,
      mangledName: "_CN30ohos.arkui.component.grid_item37FfiOHOSAceFrameworkGridItemSelectableHbE5valueE",
      exportId: "",
      mangledBeforeSema: "",
      hash: {
        instVar: 0,
        virt: 0,
        sig: 0,
        srcUse: 0,
        bodyHash: 0
      },
      info_type: "ParamInfo",
      info: {
      }
    },
    {
      kind: "FuncDecl",
      isTopLevel: true,
      fullPkgName: "ohos.arkui.component.grid_item",
      genericDecl: {
        pkgId: -1,
        decl: ""
      },
      begin: {
        file: 1,
        pkgId: 0,
        line: 38,
        column: 5,
        ignore: false
      },
      end: {
        file: 1,
        pkgId: 0,
        line: 38,
        column: 64,
        ignore: false
      },
      identifier: "FfiOHOSAceFrameworkGridItemSelected",
      identifierPos: {
        file: 1,
        pkgId: 0,
        line: 38,
        column: 10,
        ignore: false
      },
      attributes: [
        144968409101123632,
        0
      ],
      annotations: [

      ],
      type: 5,
      mangledName: "FfiOHOSAceFrameworkGridItemSelected",
      exportId: "FfiOHOSAceFrameworkGridItemSelected",
      mangledBeforeSema: "30ohos.arkui.component.grid_item35FfiOHOSAceFrameworkGridItemSelectedFb$$u",
      hash: {
        instVar: 0,
        virt: 0,
        sig: 520285295869893810,
        srcUse: 7222278799635774413,
        bodyHash: 8408041226178326877
      },
      info_type: "FuncInfo",
      info: {
        funcBody: {
          paramLists: [
            {
              params: [
                17
              ],
              desugars: [
                0
              ]
            }
          ],
          retType: 2
        }
      }
    },
    {
      kind: "FuncParam",
      fullPkgName: "ohos.arkui.component.grid_item",
      begin: {
        file: 1,
        pkgId: 0,
        line: 38,
        column: 46,
        ignore: false
      },
      end: {
        file: 1,
        pkgId: 0,
        line: 38,
        column: 57,
        ignore: false
      },
      identifier: "value",
      identifierPos: {
        file: 1,
        pkgId: 0,
        line: 38,
        column: 46,
        ignore: false
      },
      attributes: [
        562949953421344,
        0
      ],
      annotations: [

      ],
      type: 6,
      mangledName: "_CN30ohos.arkui.component.grid_item35FfiOHOSAceFrameworkGridItemSelectedHbE5valueE",
      exportId: "",
      mangledBeforeSema: "",
      hash: {
        instVar: 0,
        virt: 0,
        sig: 0,
        srcUse: 0,
        bodyHash: 0
      },
      info_type: "ParamInfo",
      info: {
      }
    },
    {
      kind: "FuncDecl",
      isTopLevel: true,
      fullPkgName: "ohos.arkui.component.grid_item",
      genericDecl: {
        pkgId: -1,
        decl: ""
      },
      begin: {
        file: 1,
        pkgId: 0,
        line: 40,
        column: 5,
        ignore: false
      },
      end: {
        file: 1,
        pkgId: 0,
        line: 40,
        column: 68,
        ignore: false
      },
      identifier: "FfiOHOSAceFrameworkGridItemOnSelect",
      identifierPos: {
        file: 1,
        pkgId: 0,
        line: 40,
        column: 10,
        ignore: false
      },
      attributes: [
        144968409101123632,
        0
      ],
      annotations: [

      ],
      type: 7,
      mangledName: "FfiOHOSAceFrameworkGridItemOnSelect",
      exportId: "FfiOHOSAceFrameworkGridItemOnSelect",
      mangledBeforeSema: "30ohos.arkui.component.grid_item35FfiOHOSAceFrameworkGridItemOnSelectFl$$u",
      hash: {
        instVar: 0,
        virt: 0,
        sig: 520285295869893810,
        srcUse: 7222278799635774413,
        bodyHash: 5609522965981233593
      },
      info_type: "FuncInfo",
      info: {
        funcBody: {
          paramLists: [
            {
              params: [
                19
              ],
              desugars: [
                0
              ]
            }
          ],
          retType: 2
        }
      }
    },
    {
      kind: "FuncParam",
      fullPkgName: "ohos.arkui.component.grid_item",
      begin: {
        file: 1,
        pkgId: 0,
        line: 40,
        column: 46,
        ignore: false
      },
      end: {
        file: 1,
        pkgId: 0,
        line: 40,
        column: 61,
        ignore: false
      },
      identifier: "callback",
      identifierPos: {
        file: 1,
        pkgId: 0,
        line: 40,
        column: 46,
        ignore: false
      },
      attributes: [
        562949953421344,
        0
      ],
      annotations: [

      ],
      type: 8,
      mangledName: "_CN30ohos.arkui.component.grid_item35FfiOHOSAceFrameworkGridItemOnSelectHlE8callbackE",
      exportId: "",
      mangledBeforeSema: "",
      hash: {
        instVar: 0,
        virt: 0,
        sig: 0,
        srcUse: 0,
        bodyHash: 0
      },
      info_type: "ParamInfo",
      info: {
      }
    },
    {
      kind: "ClassDecl",
      isTopLevel: true,
      fullPkgName: "ohos.arkui.component.grid_item",
      genericDecl: {
        pkgId: -1,
        decl: ""
      },
      begin: {
        file: 1,
        pkgId: 0,
        line: 53,
        column: 1,
        ignore: false
      },
      end: {
        file: 1,
        pkgId: 0,
        line: 166,
        column: 2,
        ignore: false
      },
      identifier: "GridItem",
      identifierPos: {
        file: 1,
        pkgId: 0,
        line: 53,
        column: 19,
        ignore: false
      },
      attributes: [
        144678412907709488,
        0
      ],
      annotations: [
        {
          kind: "Custom",
          identifier: "APILevel",
          args: [
            {
              name: "",
              expr: 1
            },
            {
              name: "stagemodelonly",
              expr: 2
            },
            {
              name: "syscap",
              expr: 3
            }
          ]
        }
      ],
      type: 9,
      mangledName: "_CN30ohos.arkui.component.grid_item8GridItemE",
      exportId: "_CN30ohos.arkui.component.grid_item8GridItemE",
      mangledBeforeSema: "30ohos.arkui.component.grid_item8GridItemC",
      hash: {
        instVar: 0,
        virt: 0,
        sig: 6438789364046432450,
        srcUse: 6029406924600920868,
        bodyHash: 1133939644320979027
      },
      info_type: "ClassInfo",
      info: {
        inheritedTypes: [
          15
        ],
        body: [
          21,
          22,
          24,
          26,
          28,
          30
        ]
      }
    },
    {
      kind: "FuncDecl",
      fullPkgName: "ohos.arkui.component.grid_item",
      genericDecl: {
        pkgId: -1,
        decl: ""
      },
      begin: {
        file: 1,
        pkgId: 0,
        line: 66,
        column: 5,
        ignore: false
      },
      end: {
        file: 1,
        pkgId: 0,
        line: 70,
        column: 6,
        ignore: false
      },
      identifier: "init",
      identifierPos: {
        file: 1,
        pkgId: 0,
        line: 66,
        column: 12,
        ignore: false
      },
      attributes: [
        144678140445197344,
        0
      ],
      annotations: [
        {
          kind: "Custom",
          identifier: "APILevel",
          args: [
            {
              name: "",
              expr: 4
            },
            {
              name: "stagemodelonly",
              expr: 5
            },
            {
              name: "syscap",
              expr: 6
            }
          ]
        }
      ],
      type: 10,
      mangledName: "_CN30ohos.arkui.component.grid_item8GridItem6<init>Hv",
      exportId: "_CN30ohos.arkui.component.grid_item8GridItem6<init>Hv",
      mangledBeforeSema: "30ohos.arkui.component.grid_item8GridItemC6<init>F$$",
      hash: {
        instVar: 0,
        virt: 0,
        sig: 14151301873218655650,
        srcUse: 0,
        bodyHash: 17014571914401731895
      },
      info_type: "FuncInfo",
      info: {
        funcBody: {
          paramLists: [
            {
              params: [

              ],
              desugars: [

              ]
            }
          ],
          retType: 9
        }
      }
    },
    {
      kind: "FuncDecl",
      fullPkgName: "ohos.arkui.component.grid_item",
      genericDecl: {
        pkgId: -1,
        decl: ""
      },
      begin: {
        file: 1,
        pkgId: 0,
        line: 84,
        column: 5,
        ignore: false
      },
      end: {
        file: 1,
        pkgId: 0,
        line: 89,
        column: 6,
        ignore: false
      },
      identifier: "init",
      identifierPos: {
        file: 1,
        pkgId: 0,
        line: 84,
        column: 12,
        ignore: false
      },
      attributes: [
        144678140445197344,
        0
      ],
      annotations: [
        {
          kind: "Custom",
          identifier: "APILevel",
          args: [
            {
              name: "",
              expr: 7
            },
            {
              name: "stagemodelonly",
              expr: 8
            },
            {
              name: "syscap",
              expr: 9
            }
          ]
        }
      ],
      type: 11,
      mangledName: "_CN30ohos.arkui.component.grid_item8GridItem6<init>HF0uE",
      exportId: "_CN30ohos.arkui.component.grid_item8GridItem6<init>HF0uE",
      mangledBeforeSema: "30ohos.arkui.component.grid_item8GridItemC6<init>FFu$$",
      hash: {
        instVar: 0,
        virt: 0,
        sig: 14151301873218655650,
        srcUse: 0,
        bodyHash: 15666997054206596548
      },
      info_type: "FuncInfo",
      info: {
        funcBody: {
          paramLists: [
            {
              params: [
                23
              ],
              desugars: [
                0
              ]
            }
          ],
          retType: 9
        }
      }
    },
    {
      kind: "FuncParam",
      fullPkgName: "ohos.arkui.component.grid_item",
      begin: {
        file: 1,
        pkgId: 0,
        line: 84,
        column: 17,
        ignore: false
      },
      end: {
        file: 1,
        pkgId: 0,
        line: 84,
        column: 34,
        ignore: false
      },
      identifier: "child",
      identifierPos: {
        file: 1,
        pkgId: 0,
        line: 84,
        column: 17,
        ignore: false
      },
      attributes: [
        562949953421344,
        0
      ],
      annotations: [

      ],
      type: 12,
      mangledName: "_CN30ohos.arkui.component.grid_item8GridItem4initHF0uEE5childE",
      exportId: "",
      mangledBeforeSema: "",
      hash: {
        instVar: 0,
        virt: 0,
        sig: 0,
        srcUse: 0,
        bodyHash: 0
      },
      info_type: "ParamInfo",
      info: {
      }
    },
    {
      kind: "FuncDecl",
      fullPkgName: "ohos.arkui.component.grid_item",
      genericDecl: {
        pkgId: -1,
        decl: ""
      },
      begin: {
        file: 1,
        pkgId: 0,
        line: 103,
        column: 5,
        ignore: false
      },
      end: {
        file: 1,
        pkgId: 0,
        line: 108,
        column: 6,
        ignore: false
      },
      identifier: "columnStart",
      identifierPos: {
        file: 1,
        pkgId: 0,
        line: 103,
        column: 17,
        ignore: false
      },
      attributes: [
        144678138297713696,
        0
      ],
      annotations: [
        {
          kind: "Custom",
          identifier: "APILevel",
          args: [
            {
              name: "",
              expr: 10
            },
            {
              name: "stagemodelonly",
              expr: 11
            },
            {
              name: "syscap",
              expr: 12
            }
          ]
        }
      ],
      type: 13,
      mangledName: "_CN30ohos.arkui.component.grid_item8GridItem11columnStartHi",
      exportId: "_CN30ohos.arkui.component.grid_item8GridItem11columnStartHi",
      mangledBeforeSema: "30ohos.arkui.component.grid_item8GridItemC11columnStartFi$$H",
      hash: {
        instVar: 0,
        virt: 0,
        sig: 14151301873218655650,
        srcUse: 0,
        bodyHash: 11913496499648372211
      },
      info_type: "FuncInfo",
      info: {
        funcBody: {
          paramLists: [
            {
              params: [
                25
              ],
              desugars: [
                0
              ]
            }
          ],
          retType: 14
        }
      }
    },
    {
      kind: "FuncParam",
      fullPkgName: "ohos.arkui.component.grid_item",
      begin: {
        file: 1,
        pkgId: 0,
        line: 103,
        column: 29,
        ignore: false
      },
      end: {
        file: 1,
        pkgId: 0,
        line: 103,
        column: 47,
        ignore: false
      },
      identifier: "columnStart",
      identifierPos: {
        file: 1,
        pkgId: 0,
        line: 103,
        column: 29,
        ignore: false
      },
      attributes: [
        562949953421344,
        0
      ],
      annotations: [

      ],
      type: 4,
      mangledName: "_CN30ohos.arkui.component.grid_item8GridItem11columnStartHiEY2_E",
      exportId: "",
      mangledBeforeSema: "",
      hash: {
        instVar: 0,
        virt: 0,
        sig: 0,
        srcUse: 0,
        bodyHash: 0
      },
      info_type: "ParamInfo",
      info: {
      }
    },
    {
      kind: "FuncDecl",
      fullPkgName: "ohos.arkui.component.grid_item",
      genericDecl: {
        pkgId: -1,
        decl: ""
      },
      begin: {
        file: 1,
        pkgId: 0,
        line: 122,
        column: 5,
        ignore: false
      },
      end: {
        file: 1,
        pkgId: 0,
        line: 127,
        column: 6,
        ignore: false
      },
      identifier: "columnEnd",
      identifierPos: {
        file: 1,
        pkgId: 0,
        line: 122,
        column: 17,
        ignore: false
      },
      attributes: [
        144678138297713696,
        0
      ],
      annotations: [
        {
          kind: "Custom",
          identifier: "APILevel",
          args: [
            {
              name: "",
              expr: 13
            },
            {
              name: "stagemodelonly",
              expr: 14
            },
            {
              name: "syscap",
              expr: 15
            }
          ]
        }
      ],
      type: 13,
      mangledName: "_CN30ohos.arkui.component.grid_item8GridItem9columnEndHi",
      exportId: "_CN30ohos.arkui.component.grid_item8GridItem9columnEndHi",
      mangledBeforeSema: "30ohos.arkui.component.grid_item8GridItemC9columnEndFi$$H",
      hash: {
        instVar: 0,
        virt: 0,
        sig: 14151301873218655650,
        srcUse: 0,
        bodyHash: 7254786001896400390
      },
      info_type: "FuncInfo",
      info: {
        funcBody: {
          paramLists: [
            {
              params: [
                27
              ],
              desugars: [
                0
              ]
            }
          ],
          retType: 14
        }
      }
    },
    {
      kind: "FuncParam",
      fullPkgName: "ohos.arkui.component.grid_item",
      begin: {
        file: 1,
        pkgId: 0,
        line: 122,
        column: 27,
        ignore: false
      },
      end: {
        file: 1,
        pkgId: 0,
        line: 122,
        column: 43,
        ignore: false
      },
      identifier: "columnEnd",
      identifierPos: {
        file: 1,
        pkgId: 0,
        line: 122,
        column: 27,
        ignore: false
      },
      attributes: [
        562949953421344,
        0
      ],
      annotations: [

      ],
      type: 4,
      mangledName: "_CN30ohos.arkui.component.grid_item8GridItem9columnEndHiEY2_E",
      exportId: "",
      mangledBeforeSema: "",
      hash: {
        instVar: 0,
        virt: 0,
        sig: 0,
        srcUse: 0,
        bodyHash: 0
      },
      info_type: "ParamInfo",
      info: {
      }
    },
    {
      kind: "FuncDecl",
      fullPkgName: "ohos.arkui.component.grid_item",
      genericDecl: {
        pkgId: -1,
        decl: ""
      },
      begin: {
        file: 1,
        pkgId: 0,
        line: 141,
        column: 5,
        ignore: false
      },
      end: {
        file: 1,
        pkgId: 0,
        line: 146,
        column: 6,
        ignore: false
      },
      identifier: "rowStart",
      identifierPos: {
        file: 1,
        pkgId: 0,
        line: 141,
        column: 17,
        ignore: false
      },
      attributes: [
        144678138297713696,
        0
      ],
      annotations: [
        {
          kind: "Custom",
          identifier: "APILevel",
          args: [
            {
              name: "",
              expr: 16
            },
            {
              name: "stagemodelonly",
              expr: 17
            },
            {
              name: "syscap",
              expr: 18
            }
          ]
        }
      ],
      type: 13,
      mangledName: "_CN30ohos.arkui.component.grid_item8GridItem8rowStartHi",
      exportId: "_CN30ohos.arkui.component.grid_item8GridItem8rowStartHi",
      mangledBeforeSema: "30ohos.arkui.component.grid_item8GridItemC8rowStartFi$$H",
      hash: {
        instVar: 0,
        virt: 0,
        sig: 14151301873218655650,
        srcUse: 0,
        bodyHash: 338599584175412866
      },
      info_type: "FuncInfo",
      info: {
        funcBody: {
          paramLists: [
            {
              params: [
                29
              ],
              desugars: [
                0
              ]
            }
          ],
          retType: 14
        }
      }
    },
    {
      kind: "FuncParam",
      fullPkgName: "ohos.arkui.component.grid_item",
      begin: {
        file: 1,
        pkgId: 0,
        line: 141,
        column: 26,
        ignore: false
      },
      end: {
        file: 1,
        pkgId: 0,
        line: 141,
        column: 41,
        ignore: false
      },
      identifier: "rowStart",
      identifierPos: {
        file: 1,
        pkgId: 0,
        line: 141,
        column: 26,
        ignore: false
      },
      attributes: [
        562949953421344,
        0
      ],
      annotations: [

      ],
      type: 4,
      mangledName: "_CN30ohos.arkui.component.grid_item8GridItem8rowStartHiEY2_E",
      exportId: "",
      mangledBeforeSema: "",
      hash: {
        instVar: 0,
        virt: 0,
        sig: 0,
        srcUse: 0,
        bodyHash: 0
      },
      info_type: "ParamInfo",
      info: {
      }
    },
    {
      kind: "FuncDecl",
      fullPkgName: "ohos.arkui.component.grid_item",
      genericDecl: {
        pkgId: -1,
        decl: ""
      },
      begin: {
        file: 1,
        pkgId: 0,
        line: 160,
        column: 5,
        ignore: false
      },
      end: {
        file: 1,
        pkgId: 0,
        line: 165,
        column: 6,
        ignore: false
      },
      identifier: "rowEnd",
      identifierPos: {
        file: 1,
        pkgId: 0,
        line: 160,
        column: 17,
        ignore: false
      },
      attributes: [
        144678138297713696,
        0
      ],
      annotations: [
        {
          kind: "Custom",
          identifier: "APILevel",
          args: [
            {
              name: "",
              expr: 19
            },
            {
              name: "stagemodelonly",
              expr: 20
            },
            {
              name: "syscap",
              expr: 21
            }
          ]
        }
      ],
      type: 13,
      mangledName: "_CN30ohos.arkui.component.grid_item8GridItem6rowEndHi",
      exportId: "_CN30ohos.arkui.component.grid_item8GridItem6rowEndHi",
      mangledBeforeSema: "30ohos.arkui.component.grid_item8GridItemC6rowEndFi$$H",
      hash: {
        instVar: 0,
        virt: 0,
        sig: 14151301873218655650,
        srcUse: 0,
        bodyHash: 16672489483157987354
      },
      info_type: "FuncInfo",
      info: {
        funcBody: {
          paramLists: [
            {
              params: [
                31
              ],
              desugars: [
                0
              ]
            }
          ],
          retType: 14
        }
      }
    },
    {
      kind: "FuncParam",
      fullPkgName: "ohos.arkui.component.grid_item",
      begin: {
        file: 1,
        pkgId: 0,
        line: 160,
        column: 24,
        ignore: false
      },
      end: {
        file: 1,
        pkgId: 0,
        line: 160,
        column: 37,
        ignore: false
      },
      identifier: "rowEnd",
      identifierPos: {
        file: 1,
        pkgId: 0,
        line: 160,
        column: 24,
        ignore: false
      },
      attributes: [
        562949953421344,
        0
      ],
      annotations: [

      ],
      type: 4,
      mangledName: "_CN30ohos.arkui.component.grid_item8GridItem6rowEndHiEY2_E",
      exportId: "",
      mangledBeforeSema: "",
      hash: {
        instVar: 0,
        virt: 0,
        sig: 0,
        srcUse: 0,
        bodyHash: 0
      },
      info_type: "ParamInfo",
      info: {
      }
    }
  ],
  allExprs: [
    {
      kind: "LitConstExpr",
      begin: {
        file: 1,
        pkgId: 0,
        line: 49,
        column: 5,
        ignore: false
      },
      end: {
        file: 1,
        pkgId: 0,
        line: 49,
        column: 7,
        ignore: false
      },
      info_type: "LitConstInfo",
      info: {
        strValue: "21"
      }
    },
    {
      kind: "LitConstExpr",
      begin: {
        file: 1,
        pkgId: 0,
        line: 50,
        column: 21,
        ignore: false
      },
      end: {
        file: 1,
        pkgId: 0,
        line: 50,
        column: 25,
        ignore: false
      },
      info_type: "LitConstInfo",
      info: {
        strValue: "true",
        constKind: "Bool"
      }
    },
    {
      kind: "LitConstExpr",
      begin: {
        file: 1,
        pkgId: 0,
        line: 51,
        column: 13,
        ignore: false
      },
      end: {
        file: 1,
        pkgId: 0,
        line: 51,
        column: 48,
        ignore: false
      },
      info_type: "LitConstInfo",
      info: {
        strValue: "SystemCapability.ArkUI.ArkUI.Full",
        constKind: "String"
      }
    },
    {
      kind: "LitConstExpr",
      begin: {
        file: 1,
        pkgId: 0,
        line: 62,
        column: 9,
        ignore: false
      },
      end: {
        file: 1,
        pkgId: 0,
        line: 62,
        column: 11,
        ignore: false
      },
      info_type: "LitConstInfo",
      info: {
        strValue: "21"
      }
    },
    {
      kind: "LitConstExpr",
      begin: {
        file: 1,
        pkgId: 0,
        line: 63,
        column: 25,
        ignore: false
      },
      end: {
        file: 1,
        pkgId: 0,
        line: 63,
        column: 29,
        ignore: false
      },
      info_type: "LitConstInfo",
      info: {
        strValue: "true",
        constKind: "Bool"
      }
    },
    {
      kind: "LitConstExpr",
      begin: {
        file: 1,
        pkgId: 0,
        line: 64,
        column: 17,
        ignore: false
      },
      end: {
        file: 1,
        pkgId: 0,
        line: 64,
        column: 52,
        ignore: false
      },
      info_type: "LitConstInfo",
      info: {
        strValue: "SystemCapability.ArkUI.ArkUI.Full",
        constKind: "String"
      }
    },
    {
      kind: "LitConstExpr",
      begin: {
        file: 1,
        pkgId: 0,
        line: 80,
        column: 9,
        ignore: false
      },
      end: {
        file: 1,
        pkgId: 0,
        line: 80,
        column: 11,
        ignore: false
      },
      info_type: "LitConstInfo",
      info: {
        strValue: "21"
      }
    },
    {
      kind: "LitConstExpr",
      begin: {
        file: 1,
        pkgId: 0,
        line: 81,
        column: 25,
        ignore: false
      },
      end: {
        file: 1,
        pkgId: 0,
        line: 81,
        column: 29,
        ignore: false
      },
      info_type: "LitConstInfo",
      info: {
        strValue: "true",
        constKind: "Bool"
      }
    },
    {
      kind: "LitConstExpr",
      begin: {
        file: 1,
        pkgId: 0,
        line: 82,
        column: 17,
        ignore: false
      },
      end: {
        file: 1,
        pkgId: 0,
        line: 82,
        column: 52,
        ignore: false
      },
      info_type: "LitConstInfo",
      info: {
        strValue: "SystemCapability.ArkUI.ArkUI.Full",
        constKind: "String"
      }
    },
    {
      kind: "LitConstExpr",
      begin: {
        file: 1,
        pkgId: 0,
        line: 99,
        column: 9,
        ignore: false
      },
      end: {
        file: 1,
        pkgId: 0,
        line: 99,
        column: 11,
        ignore: false
      },
      info_type: "LitConstInfo",
      info: {
        strValue: "21"
      }
    },
    {
      kind: "LitConstExpr",
      begin: {
        file: 1,
        pkgId: 0,
        line: 100,
        column: 25,
        ignore: false
      },
      end: {
        file: 1,
        pkgId: 0,
        line: 100,
        column: 29,
        ignore: false
      },
      info_type: "LitConstInfo",
      info: {
        strValue: "true",
        constKind: "Bool"
      }
    },
    {
      kind: "LitConstExpr",
      begin: {
        file: 1,
        pkgId: 0,
        line: 101,
        column: 17,
        ignore: false
      },
      end: {
        file: 1,
        pkgId: 0,
        line: 101,
        column: 52,
        ignore: false
      },
      info_type: "LitConstInfo",
      info: {
        strValue: "SystemCapability.ArkUI.ArkUI.Full",
        constKind: "String"
      }
    },
    {
      kind: "LitConstExpr",
      begin: {
        file: 1,
        pkgId: 0,
        line: 118,
        column: 9,
        ignore: false
      },
      end: {
        file: 1,
        pkgId: 0,
        line: 118,
        column: 11,
        ignore: false
      },
      info_type: "LitConstInfo",
      info: {
        strValue: "21"
      }
    },
    {
      kind: "LitConstExpr",
      begin: {
        file: 1,
        pkgId: 0,
        line: 119,
        column: 25,
        ignore: false
      },
      end: {
        file: 1,
        pkgId: 0,
        line: 119,
        column: 29,
        ignore: false
      },
      info_type: "LitConstInfo",
      info: {
        strValue: "true",
        constKind: "Bool"
      }
    },
    {
      kind: "LitConstExpr",
      begin: {
        file: 1,
        pkgId: 0,
        line: 120,
        column: 17,
        ignore: false
      },
      end: {
        file: 1,
        pkgId: 0,
        line: 120,
        column: 52,
        ignore: false
      },
      info_type: "LitConstInfo",
      info: {
        strValue: "SystemCapability.ArkUI.ArkUI.Full",
        constKind: "String"
      }
    },
    {
      kind: "LitConstExpr",
      begin: {
        file: 1,
        pkgId: 0,
        line: 137,
        column: 9,
        ignore: false
      },
      end: {
        file: 1,
        pkgId: 0,
        line: 137,
        column: 11,
        ignore: false
      },
      info_type: "LitConstInfo",
      info: {
        strValue: "21"
      }
    },
    {
      kind: "LitConstExpr",
      begin: {
        file: 1,
        pkgId: 0,
        line: 138,
        column: 25,
        ignore: false
      },
      end: {
        file: 1,
        pkgId: 0,
        line: 138,
        column: 29,
        ignore: false
      },
      info_type: "LitConstInfo",
      info: {
        strValue: "true",
        constKind: "Bool"
      }
    },
    {
      kind: "LitConstExpr",
      begin: {
        file: 1,
        pkgId: 0,
        line: 139,
        column: 17,
        ignore: false
      },
      end: {
        file: 1,
        pkgId: 0,
        line: 139,
        column: 52,
        ignore: false
      },
      info_type: "LitConstInfo",
      info: {
        strValue: "SystemCapability.ArkUI.ArkUI.Full",
        constKind: "String"
      }
    },
    {
      kind: "LitConstExpr",
      begin: {
        file: 1,
        pkgId: 0,
        line: 156,
        column: 9,
        ignore: false
      },
      end: {
        file: 1,
        pkgId: 0,
        line: 156,
        column: 11,
        ignore: false
      },
      info_type: "LitConstInfo",
      info: {
        strValue: "21"
      }
    },
    {
      kind: "LitConstExpr",
      begin: {
        file: 1,
        pkgId: 0,
        line: 157,
        column: 25,
        ignore: false
      },
      end: {
        file: 1,
        pkgId: 0,
        line: 157,
        column: 29,
        ignore: false
      },
      info_type: "LitConstInfo",
      info: {
        strValue: "true",
        constKind: "Bool"
      }
    },
    {
      kind: "LitConstExpr",
      begin: {
        file: 1,
        pkgId: 0,
        line: 158,
        column: 17,
        ignore: false
      },
      end: {
        file: 1,
        pkgId: 0,
        line: 158,
        column: 52,
        ignore: false
      },
      info_type: "LitConstInfo",
      info: {
        strValue: "SystemCapability.ArkUI.ArkUI.Full",
        constKind: "String"
      }
    }
  ],
  moduleName: ""
}
